MANIFEST.in
README.md
pyproject.toml
setup.py
selcol/__init__.py
selcol/file.py
selcol.egg-info/PKG-INFO
selcol.egg-info/SOURCES.txt
selcol.egg-info/dependency_links.txt
selcol.egg-info/requires.txt
selcol.egg-info/top_level.txt
selcol/pretrained/.gitignore
selcol/pretrained/pretrained-JAXON_JVRC-0cc17003e5f01cd6157233f92877ddc8-19cd5b6d-7026-41a5-b0ed-944ff9b7d6c9/metadata.json
selcol/pretrained/pretrained-JAXON_JVRC-0cc17003e5f01cd6157233f92877ddc8-19cd5b6d-7026-41a5-b0ed-944ff9b7d6c9/model-1.onnx
selcol/pretrained/pretrained-JAXON_JVRC-0cc17003e5f01cd6157233f92877ddc8-19cd5b6d-7026-41a5-b0ed-944ff9b7d6c9/model-128.onnx
selcol/pretrained/pretrained-JAXON_JVRC-0cc17003e5f01cd6157233f92877ddc8-19cd5b6d-7026-41a5-b0ed-944ff9b7d6c9/model-16.onnx
selcol/pretrained/pretrained-JAXON_JVRC-0cc17003e5f01cd6157233f92877ddc8-19cd5b6d-7026-41a5-b0ed-944ff9b7d6c9/model-32.onnx
selcol/pretrained/pretrained-JAXON_JVRC-0cc17003e5f01cd6157233f92877ddc8-19cd5b6d-7026-41a5-b0ed-944ff9b7d6c9/model-64.onnx
selcol/pretrained/pretrained-JAXON_JVRC-0cc17003e5f01cd6157233f92877ddc8-19cd5b6d-7026-41a5-b0ed-944ff9b7d6c9/model-8.onnx
selcol/pretrained/pretrained-JAXON_JVRC-0cc17003e5f01cd6157233f92877ddc8-19cd5b6d-7026-41a5-b0ed-944ff9b7d6c9/numpy_layers.pkl
selcol/pretrained/pretrained-fetch-338459c27088a928a7a3b08023474fbb-ab64c329-13bf-442f-b331-20eb21250e3b/metadata.json
selcol/pretrained/pretrained-fetch-338459c27088a928a7a3b08023474fbb-ab64c329-13bf-442f-b331-20eb21250e3b/model-1.onnx
selcol/pretrained/pretrained-fetch-338459c27088a928a7a3b08023474fbb-ab64c329-13bf-442f-b331-20eb21250e3b/model-128.onnx
selcol/pretrained/pretrained-fetch-338459c27088a928a7a3b08023474fbb-ab64c329-13bf-442f-b331-20eb21250e3b/model-16.onnx
selcol/pretrained/pretrained-fetch-338459c27088a928a7a3b08023474fbb-ab64c329-13bf-442f-b331-20eb21250e3b/model-32.onnx
selcol/pretrained/pretrained-fetch-338459c27088a928a7a3b08023474fbb-ab64c329-13bf-442f-b331-20eb21250e3b/model-64.onnx
selcol/pretrained/pretrained-fetch-338459c27088a928a7a3b08023474fbb-ab64c329-13bf-442f-b331-20eb21250e3b/model-8.onnx
