Metadata-Version: 2.1
Name: selcol
Version: 0.0.4.1
Summary: yet another percol implementation
Author: Hirokazu Ishida
Author-email: h-ishida@jsk.imi.i.u-tokyo.ac.jp
License: MIT
Provides-Extra: dev
